{
  "number": 8107,
  "title": "OptProf pipeline improvements",
  "body": "Consider implementing some of the following pipeline improvements:\r\n\r\n1. The detection of vs bootstrap branch, see [PR comment](https://github.com/dotnet/msbuild/pull/8085#discussion_r1003405325).\r\n2. The LKG feature.\r\n3. Investigate and fix issue with two tests failing in opt-prof pipeline attempting to ngen `MSBuildTaskHost.dll`. See any opt-prof v2 pipeline run for a repro.\r\n4.  On the cron, target the top pipeline run for the main branch of MSBuild pipeline, instead of the top pipeline run.",
  "state": "OPEN",
  "createdAt": "2022-10-31T16:11:35Z",
  "updatedAt": "2024-01-31T08:15:53Z",
  "closedAt": null,
  "author": {
    "login": "AR-May"
  },
  "labels": [
    "Area: Our Own Build",
    "triaged"
  ],
  "assignees": {
    "nodes": []
  },
  "milestone": null,
  "comments": {
    "nodes": []
  }
}