{
  "number": 8425,
  "title": "Binlogs should include PATH",
  "body": "`PATH` can be very relevant for build debugging, since `Exec` and other process executions can depend on it, but it is not in the current \r\n\r\nhttps://github.com/dotnet/msbuild/blob/51df47643a8ee2715ac67fab8d652b25be070cd2/src/Shared/EnvironmentUtilities.cs#L16-L21\r\n\r\nWe should consider logging it.",
  "state": "OPEN",
  "createdAt": "2023-02-08T14:53:10Z",
  "updatedAt": "2025-06-02T08:29:44Z",
  "closedAt": null,
  "author": {
    "login": "rainersigwald"
  },
  "milestone": null,
  "assignees": {
    "nodes": []
  },
  "labels": [
    "Area: Logging",
    "triaged"
  ],
  "comments": {
    "nodes": []
  }
}