{
  "number": 4340,
  "title": "MSB4018\t\u201cCopySources\u201d task failed unexpectedly?",
  "body": "\r\nSystem.NullReferenceException: Object reference not set to an instance of an object\u3002\r\n   \u5728 Microsoft.Build.Linux.Tasks.RemoteToolTask.Execute()\r\n   \u5728 Microsoft.Build.BackEnd.TaskExecutionHost.Microsoft.Build.BackEnd.ITaskExecutionHost.Execute()\r\n   \u5728 Microsoft.Build.BackEnd.TaskBuilder.<ExecuteInstantiatedTask>d__26.MoveNext()\tserver\tD:\\Program Files (x86)\\Microsoft Visual Studio\\2017\\Community\\Common7\\IDE\\VC\\VCTargets\\Application Type\\Linux\\1.0\\Linux.targets\t162\t\r\n\r\n",
  "state": "CLOSED",
  "createdAt": "2019-04-30T05:11:09Z",
  "updatedAt": "2024-02-21T17:08:33Z",
  "closedAt": "2019-05-07T00:42:09Z",
  "author": {
    "login": "zuowanbushiwo"
  },
  "labels": [
    "triaged"
  ],
  "assignees": {
    "nodes": []
  },
  "milestone": {
    "title": "Discussion"
  },
  "comments": {
    "nodes": [
      {
        "body": "This looks most likely a bug in the C++ owned task. (?). @olgaark are those in another repo somewhere?",
        "createdAt": "2019-05-01T19:41:17Z",
        "updatedAt": "2019-05-01T19:41:17Z",
        "author": {
          "login": "danmoseley"
        }
      },
      {
        "body": "Looks like that to me as well. pinging @olgaark again to see what is the best way to track this.",
        "createdAt": "2019-05-06T17:25:00Z",
        "updatedAt": "2019-05-06T17:25:00Z",
        "author": {
          "login": "livarcocc"
        }
      }
    ]
  }
}