{
  "number": 2691,
  "title": "Autoimport tries to import OS-generated \"._Microsoft.Common.tasks\" on mac",
  "body": "On MACOS ._Microsoft.Common.tasks file may be generated by OS itself.\r\nMore [info](https://stackoverflow.com/questions/10323580/what-are-all-these-hidden-prefixed-files-that-are-in-my-git-repo) about \"dot underscore files\".\r\n[error.txt](https://github.com/Microsoft/msbuild/files/1437118/error.txt)\r\n\r\nTo reproduce:\r\nCreate  ._Microsoft.Common.tasks near  Microsoft.Common.tasks in \"msbuild/15.0/bin\"\r\n\r\n",
  "state": "CLOSED",
  "createdAt": "2017-11-02T09:24:52Z",
  "updatedAt": "2024-02-21T17:15:53Z",
  "closedAt": "2020-03-23T15:37:53Z",
  "author": {
    "login": "van800"
  },
  "labels": [
    "triaged"
  ],
  "assignees": {
    "nodes": []
  },
  "milestone": null,
  "comments": {
    "nodes": [
      {
        "body": "Team triage: closing due to age. If this is causing problems for you, please let us know and we can reactivate it.",
        "createdAt": "2020-03-23T15:37:53Z",
        "updatedAt": "2020-03-23T15:37:53Z",
        "author": {
          "login": "rainersigwald"
        }
      }
    ]
  }
}