{
  "number": 11480,
  "title": "Integrate the initial Tasks/Targets metric to the new telemetry infra",
  "body": "### Context\n\nIntegrate https://github.com/dotnet/msbuild/pull/11359 into https://github.com/dotnet/msbuild/pull/11255",
  "state": "CLOSED",
  "createdAt": "2025-02-21T17:38:25Z",
  "updatedAt": "2025-02-26T12:47:35Z",
  "closedAt": "2025-02-26T12:47:35Z",
  "author": {
    "login": "JanKrivanek"
  },
  "milestone": null,
  "assignees": {
    "nodes": [
      {
        "login": "JanKrivanek"
      },
      {
        "login": "JanProvaznik"
      }
    ]
  },
  "labels": [],
  "comments": {
    "nodes": [
      {
        "body": "Work left on @JanProvaznik: https://github.com/dotnet/msbuild/pull/11481#issuecomment-2678647587",
        "createdAt": "2025-02-24T14:44:22Z",
        "author": {
          "login": "JanKrivanek"
        }
      }
    ]
  }
}