{
  "number": 9091,
  "title": "[BinFmt] Support extended messages in binary log and binary viewer",
  "body": "#8917 will introduce new internal EventArgs `Extended*EventArgs`\r\nIn context of PR such events are stored in binary log as existing corresponding non extended `*EventArgs`.\r\n\r\nAs there is certain value in showing exteneded event data in binary log we need to:\r\n- [x] create new binary log events\r\n- [x] de/ser those\r\n- [x] bump up [`FileFormat`](https://github.com/dotnet/msbuild/blob/main/src/Build/Logging/BinaryLogger/BinaryLogger.cs#L63)\r\n- [x] facilitate updating binary log viewer to support those",
  "state": "CLOSED",
  "createdAt": "2023-08-01T11:57:51Z",
  "updatedAt": "2024-02-21T16:58:51Z",
  "closedAt": "2023-10-02T11:32:28Z",
  "author": {
    "login": "rokonec"
  },
  "labels": [
    "triaged"
  ],
  "assignees": {
    "nodes": [
      {
        "login": "rokonec"
      }
    ]
  },
  "milestone": null,
  "comments": {
    "nodes": []
  }
}