{
  "number": 10695,
  "title": "[Wording only] Adjust ProjectElement assertion wording",
  "body": "### Context\r\n\r\nWe have over dozen of checks with following wording:\r\n\r\n```\r\nErrorUtilities.VerifyThrow(Link == null, \"External project\");\r\n```\r\n\r\nIt's bit criptic and need code investigation to find the reason. Let's clarify the wording\r\n\r\nMore details: https://github.com/dotnet/msbuild/pull/10673#discussion_r1769004507\r\n",
  "state": "CLOSED",
  "createdAt": "2024-09-24T09:03:59Z",
  "updatedAt": "2024-10-04T08:42:23Z",
  "closedAt": "2024-10-04T08:42:22Z",
  "author": {
    "login": "JanKrivanek"
  },
  "labels": [
    "triaged"
  ],
  "assignees": {
    "nodes": [
      {
        "login": "JanKrivanek"
      }
    ]
  },
  "milestone": null,
  "comments": {
    "nodes": []
  }
}