{
  "number": 3223,
  "title": "15.7 final loc update",
  "body": "We need a final loc update for 15.7 RTM.",
  "state": "CLOSED",
  "createdAt": "2018-04-24T16:45:01Z",
  "updatedAt": "2024-02-21T17:13:28Z",
  "closedAt": "2018-04-25T16:26:32Z",
  "author": {
    "login": "rainersigwald"
  },
  "labels": [
    "triaged"
  ],
  "assignees": {
    "nodes": [
      {
        "login": "cdmihai"
      }
    ]
  },
  "milestone": {
    "title": "MSBuild 15.7"
  },
  "comments": {
    "nodes": [
      {
        "body": "Rejected by VS shiproom, so we'll continue with the normal loc schedule for 15.8.",
        "createdAt": "2018-04-25T16:26:32Z",
        "updatedAt": "2018-04-25T16:26:32Z",
        "author": {
          "login": "rainersigwald"
        }
      }
    ]
  }
}