{
  "number": 3968,
  "title": "ToolTask that fail ValidateParameters fail \"silently\" ",
  "body": "If you have a ToolTask with ValidateParameters that returns false (and does not log) then you get an output like this:\r\n\r\n```\r\nUsing \"FooTask\" task from assembly \"Foo.dll\".\r\nTask \"FooTask\" (TaskId:14)\r\n  Task Parameter:OutputDirectory=obj/Debug/foo (TaskId:14)\r\nDone executing task \"FooTask\" -- FAILED. (TaskId:14)\r\nDone building target \"Foo\" in project \"sample-xm.csproj\" -- FAILED.: (TargetId:33)\r\n```\r\n\r\nIt would be nice if it printed \"Task X failed parameter validation\" or something. ",
  "state": "CLOSED",
  "createdAt": "2018-11-29T21:45:29Z",
  "updatedAt": "2024-02-21T17:10:14Z",
  "closedAt": "2018-12-11T19:53:49Z",
  "author": {
    "login": "chamons"
  },
  "labels": [
    "triaged"
  ],
  "assignees": {
    "nodes": []
  },
  "milestone": null,
  "comments": {
    "nodes": []
  }
}