{
  "number": 4589,
  "title": "[Source Build] Add Microsoft.Build.Localization",
  "body": "We need to produce the satellite assembly package in source build. \r\n",
  "state": "CLOSED",
  "createdAt": "2019-08-06T15:23:13Z",
  "updatedAt": "2024-02-21T17:07:38Z",
  "closedAt": "2019-09-10T20:24:39Z",
  "author": {
    "login": "nguerrera"
  },
  "labels": [
    "Area: Our Own Build",
    "triaged"
  ],
  "assignees": {
    "nodes": [
      {
        "login": "nguerrera"
      }
    ]
  },
  "milestone": {
    "title": "MSBuild 16.4"
  },
  "comments": {
    "nodes": [
      {
        "body": "Moving to 16.4 as source-build already patches 16.3",
        "createdAt": "2019-09-10T18:03:22Z",
        "updatedAt": "2019-09-10T18:03:22Z",
        "author": {
          "login": "nguerrera"
        }
      }
    ]
  }
}