{
  "number": 11357,
  "title": "Enable MSBuild Server for partner .NET repos",
  "body": "We should send PRs to enable\n\n* runtime\n* aspnetcore\n* roslyn\n* sdk\n\nAnd investigate the impact",
  "state": "OPEN",
  "createdAt": "2025-01-29T15:11:31Z",
  "updatedAt": "2025-02-04T09:41:49Z",
  "closedAt": null,
  "author": {
    "login": "baronfel"
  },
  "milestone": null,
  "assignees": {
    "nodes": []
  },
  "labels": [
    "Area: Server",
    "triaged"
  ],
  "comments": {
    "nodes": []
  }
}