{
  "number": 7646,
  "title": "Investigate MSBuild Server for memory leaks.",
  "body": "",
  "state": "CLOSED",
  "createdAt": "2022-05-23T14:13:34Z",
  "updatedAt": "2024-02-21T14:08:42Z",
  "closedAt": "2022-05-30T12:03:48Z",
  "author": {
    "login": "AR-May"
  },
  "labels": [
    "Area: Performance",
    "triaged"
  ],
  "assignees": {
    "nodes": [
      {
        "login": "Forgind"
      },
      {
        "login": "rokonec"
      },
      {
        "login": "AR-May"
      }
    ]
  },
  "milestone": null,
  "comments": {
    "nodes": [
      {
        "body": "After merging https://github.com/dotnet/msbuild/pull/7655 MSBuild server does not show any symptoms of memory leak anymore.",
        "createdAt": "2022-06-01T13:28:39Z",
        "updatedAt": "2022-06-01T13:28:39Z",
        "author": {
          "login": "rokonec"
        }
      }
    ]
  }
}