{
  "number": 7994,
  "title": "-targets flag doesn't list targets, seems to be trying to do a complete compile",
  "body": "The -targets flag doesn't list targets, seems to be trying to do a complete compile\r\n\r\nmsbuild Reliability.sln -targets\r\n\r\nExpect a list of targets, but it starts compiling everything.\r\n\r\nMSBuild version 17.3.1+2badb37d1 for .NET Framework\r\n17.3.1.41501\r\n\r\nI'm talking about this flag:\r\n\r\n  -targets[:file]\r\n                     Prints a list of available targets without executing the\r\n                     actual build process. By default the output is written to\r\n                     the console window. If the path to an output file\r\n                     is provided that will be used instead.\r\n                     (Short form: -ts)\r\n                     Example:\r\n                       -ts:out.txt",
  "state": "CLOSED",
  "createdAt": "2022-09-21T13:04:34Z",
  "updatedAt": "2022-09-21T14:29:04Z",
  "closedAt": "2022-09-21T14:29:04Z",
  "author": {
    "login": "DerekSMorin"
  },
  "labels": [
    "bug",
    "needs-triage"
  ],
  "assignees": {
    "nodes": []
  },
  "milestone": null,
  "comments": {
    "nodes": [
      {
        "body": "Duplicate of #7697",
        "createdAt": "2022-09-21T14:29:04Z",
        "updatedAt": "2022-09-21T14:29:04Z",
        "author": {
          "login": "rainersigwald"
        }
      }
    ]
  }
}