{
  "number": 11290,
  "title": "Grace handle custom ToString issues",
  "body": "Fixes #11242\r\n\r\n### Context\r\nPreventing unhandled exceptions during logging that might be comming from ToString on arbitrary types.\r\n",
  "state": "MERGED",
  "createdAt": "2025-01-15T15:14:02Z",
  "updatedAt": "2025-01-20T08:52:57Z",
  "closedAt": "2025-01-20T08:52:56Z",
  "mergedAt": "2025-01-20T08:52:56Z",
  "additions": 11,
  "deletions": 1,
  "changedFiles": 1,
  "headRefName": "proto/logger-exc",
  "isDraft": false,
  "author": {
    "login": "JanKrivanek"
  },
  "milestone": null,
  "assignees": {
    "nodes": []
  },
  "labels": [],
  "commits": {
    "nodes": [
      {
        "commit": {
          "oid": "bf81f0f8f091c9f5818397bc9ddc37c1fbef28b7",
          "message": "Grace handle custom ToString issues",
          "committedDate": "2025-01-15T15:14:50Z",
          "author": {
            "name": "Jan Krivanek",
            "email": "jankrivanek@microsoft.com"
          }
        }
      }
    ]
  },
  "comments": {
    "nodes": []
  },
  "reviewThreads": {
    "nodes": []
  }
}