{
  "number": 11685,
  "title": "[main] Update dependencies from dotnet/source-build-reference-packages",
  "body": "This pull request updates the following dependencies\n\n[marker]: <> (Begin:a86f9f27-acb1-4618-eed7-08db6775ce49)\n## From https://github.com/dotnet/source-build-reference-packages\n- **Subscription**: [a86f9f27-acb1-4618-eed7-08db6775ce49](https://maestro.dot.net/subscriptions?search=a86f9f27-acb1-4618-eed7-08db6775ce49)\n- **Build**: [20250404.3](https://dev.azure.com/dnceng/internal/_build/results?buildId=2679534)\n- **Date Produced**: April 4, 2025 8:15:34 PM UTC\n- **Commit**: [643689c88b1d5a0f1561383972c4189a0c673abe](https://github.com/dotnet/source-build-reference-packages/commit/643689c88b1d5a0f1561383972c4189a0c673abe)\n- **Branch**: refs/heads/release/9.0\n\n[DependencyUpdate]: <> (Begin)\n\n- **Updates**:\n  - **Microsoft.SourceBuild.Intermediate.source-build-reference-packages**: [from 9.0.0-alpha.1.25170.3 to 9.0.0-alpha.1.25204.3][1]\n\n[1]: https://github.com/dotnet/source-build-reference-packages/compare/6968f7059f...643689c88b\n\n[DependencyUpdate]: <> (End)\n\n\n[marker]: <> (End:a86f9f27-acb1-4618-eed7-08db6775ce49)\n\n",
  "state": "MERGED",
  "createdAt": "2025-04-04T20:57:08Z",
  "updatedAt": "2025-04-04T21:41:53Z",
  "closedAt": "2025-04-04T21:41:51Z",
  "mergedAt": "2025-04-04T21:41:51Z",
  "additions": 2,
  "deletions": 2,
  "changedFiles": 1,
  "headRefName": "darc-main-3e0a066d-deef-4d1a-bf52-de079b76608d",
  "isDraft": false,
  "author": {
    "login": "dotnet-maestro"
  },
  "milestone": null,
  "assignees": {
    "nodes": []
  },
  "labels": [],
  "commits": {
    "nodes": [
      {
        "commit": {
          "oid": "87310029903edab1e36fe03305ee65e9ab77e7a0",
          "message": "Update dependencies from https://github.com/dotnet/source-build-reference-packages build 20250404.3\n\nMicrosoft.SourceBuild.Intermediate.source-build-reference-packages\n From Version 9.0.0-alpha.1.25170.3 -> To Version 9.0.0-alpha.1.25204.3",
          "committedDate": "2025-04-04T20:57:07Z",
          "author": {
            "name": "dotnet-maestro[bot]",
            "email": "dotnet-maestro[bot]@users.noreply.github.com"
          }
        }
      }
    ]
  },
  "comments": {
    "nodes": []
  },
  "reviewThreads": {
    "nodes": []
  }
}