{
  "number": 10889,
  "title": "Stop overriding Arcade VSSDK",
  "body": "This was needed long ago but Arcade bumped past this in https://github.com/dotnet/arcade/pull/7056.\n",
  "state": "MERGED",
  "createdAt": "2024-10-25T14:26:42Z",
  "updatedAt": "2024-10-29T10:44:33Z",
  "closedAt": "2024-10-29T10:44:32Z",
  "mergedAt": "2024-10-29T10:44:32Z",
  "additions": 0,
  "deletions": 3,
  "changedFiles": 1,
  "headRefName": "stop-overriding-vssdk",
  "isDraft": false,
  "author": {
    "login": "rainersigwald"
  },
  "milestone": null,
  "assignees": {
    "nodes": []
  },
  "labels": [],
  "commits": {
    "nodes": [
      {
        "commit": {
          "oid": "4ba13525fd0b8d2e20be8d975237f1959072324d",
          "message": "Stop overriding Arcade VSSDK\n\nThis was needed long ago but Arcade bumped past this in https://github.com/dotnet/arcade/pull/7056.",
          "committedDate": "2024-10-25T14:26:25Z",
          "author": {
            "name": "Rainer Sigwald",
            "email": "raines@microsoft.com"
          }
        }
      }
    ]
  },
  "comments": {
    "nodes": [
      {
        "body": "Internal tests on experimental VS insertion look fine: https://devdiv.visualstudio.com/DevDiv/_git/VS/pullrequest/588043.",
        "createdAt": "2024-10-28T15:28:01Z",
        "author": {
          "login": "rainersigwald"
        }
      }
    ]
  },
  "reviewThreads": {
    "nodes": []
  }
}