{
  "number": 11581,
  "title": "Update MicrosoftBuildVersion in analyzer template",
  "body": "[Automated] Update the MicrosoftBuildVersion defaultValue in the template.json.",
  "state": "MERGED",
  "createdAt": "2025-03-12T02:01:54Z",
  "updatedAt": "2025-03-13T10:10:14Z",
  "closedAt": "2025-03-13T10:10:10Z",
  "mergedAt": "2025-03-13T10:10:10Z",
  "additions": 1,
  "deletions": 1,
  "changedFiles": 1,
  "headRefName": "main-update-msbuild-version-for-analyzer-template",
  "isDraft": false,
  "author": {
    "login": "github-actions"
  },
  "milestone": null,
  "assignees": {
    "nodes": []
  },
  "labels": [],
  "commits": {
    "nodes": [
      {
        "commit": {
          "oid": "306b66f7a796a4326e1aa095081f3af5ab47c334",
          "message": "Update MicrosoftBuildVersion to 17.14.0",
          "committedDate": "2025-03-12T02:01:53Z",
          "author": {
            "name": "github-actions",
            "email": "github-actions@github.com"
          }
        }
      },
      {
        "commit": {
          "oid": "2155ed838f0d125c1a4e36f80a1338254097b895",
          "message": "Merge branch 'main' into main-update-msbuild-version-for-analyzer-template",
          "committedDate": "2025-03-13T05:58:03Z",
          "author": {
            "name": "Jenny Bai",
            "email": "v-jennybai@microsoft.com"
          }
        }
      }
    ]
  },
  "comments": {
    "nodes": []
  },
  "reviewThreads": {
    "nodes": []
  }
}