{
  "number": 10807,
  "title": "[vs17.3] Update dependencies from dotnet/arcade",
  "body": "This pull request updates the following dependencies\r\n\r\n[marker]: <> (Begin:c27c7a09-2781-4064-8ede-41c6b3e57a32)\r\n## From https://github.com/dotnet/arcade\r\n- **Subscription**: c27c7a09-2781-4064-8ede-41c6b3e57a32\r\n- **Build**: 20241008.2\r\n- **Date Produced**: October 8, 2024 6:57:12 PM UTC\r\n- **Commit**: bb06ac242cf3faf5cef64127bdd11c3a4f060c06\r\n- **Branch**: refs/heads/release/6.0\r\n\r\n[DependencyUpdate]: <> (Begin)\r\n\r\n- **Updates**:\r\n  - **Microsoft.DotNet.Arcade.Sdk**: [from 6.0.0-beta.24176.9 to 6.0.0-beta.24508.2][1]\r\n  - **Microsoft.DotNet.XUnitExtensions**: [from 6.0.0-beta.24176.9 to 6.0.0-beta.24508.2][1]\r\n\r\n[1]: https://github.com/dotnet/arcade/compare/e438144bbf...bb06ac242c\r\n\r\n[DependencyUpdate]: <> (End)\r\n\r\n\r\n[marker]: <> (End:c27c7a09-2781-4064-8ede-41c6b3e57a32)\r\n\r\n",
  "state": "MERGED",
  "createdAt": "2024-10-14T13:03:43Z",
  "updatedAt": "2024-10-14T14:02:50Z",
  "closedAt": "2024-10-14T14:02:48Z",
  "mergedAt": "2024-10-14T14:02:48Z",
  "additions": 524,
  "deletions": 381,
  "changedFiles": 40,
  "headRefName": "darc-vs17.3-b74e6105-a0d8-447b-8cdd-08809020fb62",
  "isDraft": false,
  "author": {
    "login": "dotnet-maestro"
  },
  "milestone": null,
  "assignees": {
    "nodes": []
  },
  "labels": [],
  "commits": {
    "nodes": [
      {
        "commit": {
          "oid": "1aec5299f3e59fe606f4c15e3b69078c0e880738",
          "message": "Update dependencies from https://github.com/dotnet/arcade build 20241008.2\n\nMicrosoft.DotNet.Arcade.Sdk , Microsoft.DotNet.XUnitExtensions\n From Version 6.0.0-beta.24176.9 -> To Version 6.0.0-beta.24508.2",
          "committedDate": "2024-10-14T13:03:40Z",
          "author": {
            "name": "dotnet-maestro[bot]",
            "email": "dotnet-maestro[bot]@users.noreply.github.com"
          }
        }
      }
    ]
  },
  "comments": {
    "nodes": []
  },
  "reviewThreads": {
    "nodes": []
  }
}