{
  "number": 3371,
  "title": "More code reformatting:",
  "body": "For src\\tasks\\e*-q*.cs\r\n- Code style updates (mostly automated)\r\n- Reduced .NET 1.x data structure use to reduce up- and down-casting\r\n- Reduced allocations in a couple of spots",
  "state": "MERGED",
  "createdAt": "2018-06-05T23:20:18Z",
  "updatedAt": "2021-10-12T00:01:34Z",
  "closedAt": "2018-06-07T20:53:52Z",
  "mergedAt": "2018-06-07T20:53:52Z",
  "additions": 1475,
  "deletions": 2800,
  "changedFiles": 55,
  "headRefName": "dev/erikmav/resharper4",
  "isDraft": false,
  "author": {
    "login": "erikmav"
  },
  "milestone": null,
  "assignees": {
    "nodes": []
  },
  "labels": [],
  "commits": {
    "nodes": [
      {
        "commit": {
          "oid": "8f62bc97a0f2d5fb9c08d03990ff5d938f8edcb2",
          "message": "More code reformatting:\n- Code style updates (mostly automated)\n- Reduced .NET 1.x data structure use to reduce up and downcasting\n- Reduced allocations in a couple of spots",
          "committedDate": "2018-06-01T01:00:56Z",
          "author": {
            "name": "Erik Mavrinac",
            "email": "erikmav@microsoft.com"
          }
        }
      }
    ]
  },
  "comments": {
    "nodes": [
      {
        "body": "For #3320 ",
        "createdAt": "2018-06-05T23:22:55Z",
        "author": {
          "login": "erikmav"
        }
      },
      {
        "body": "@dotnet-bot test Ubuntu16.04 Build for CoreCLR please\r\n\r\n@rainersigwald uhh any idea how `Ubuntu14.04 Build for CoreCLR` could still be queuing to run?",
        "createdAt": "2018-06-06T01:58:52Z",
        "author": {
          "login": "AndyGerlicher"
        }
      }
    ]
  },
  "reviewThreads": {
    "nodes": [
      {
        "comments": {
          "nodes": [
            {
              "body": "Bunch of dangling comments wherever this refactoring ran. Sad the duplicated comments were there in the first place.",
              "createdAt": "2018-06-06T22:50:13Z",
              "path": "src/Tasks/FindInList.cs",
              "diffHunk": "@@ -18,17 +18,12 @@ public class FindInList : TaskExtension\n         // The list to search through\n         private ITaskItem[] _list;\n         // Whether to match just the file part, or the full item spec\n-        private bool _matchFileNameOnly = false;",
              "author": {
                "login": "cdmihai"
              }
            },
            {
              "body": "Fixed in following PR coming today/tomorrow, if that's OK",
              "createdAt": "2018-06-07T17:48:46Z",
              "path": "src/Tasks/FindInList.cs",
              "diffHunk": "@@ -18,17 +18,12 @@ public class FindInList : TaskExtension\n         // The list to search through\n         private ITaskItem[] _list;\n         // Whether to match just the file part, or the full item spec\n-        private bool _matchFileNameOnly = false;",
              "author": {
                "login": "erikmav"
              }
            }
          ]
        }
      }
    ]
  }
}