{
  "number": 6205,
  "title": "General \"switch\" description in help message - update for \"--\" indicator",
  "body": "This pull request updates the general \"switch\" description in the help message.\r\nThis can be considered as a follow-up of #5786 delivery, where double-dash switch indicator has been added.\r\n\r\n---\r\n\r\nThe changes contain:\r\n* Help message update: added third indicator's option and removed \"*both*\" as it's now invalid\r\n* Applied changes to the localizations\r\n\r\n",
  "state": "MERGED",
  "createdAt": "2021-03-01T18:27:45Z",
  "updatedAt": "2021-03-11T15:02:24Z",
  "closedAt": "2021-03-11T15:02:24Z",
  "mergedAt": "2021-03-11T15:02:23Z",
  "additions": 45,
  "deletions": 45,
  "changedFiles": 15,
  "headRefName": "fix-switch-help-description",
  "isDraft": false,
  "author": {
    "login": "BartoszKlonowski"
  },
  "milestone": null,
  "assignees": {
    "nodes": []
  },
  "labels": [
    "merge-when-branch-open"
  ],
  "commits": {
    "nodes": [
      {
        "commit": {
          "oid": "6405db0157c9bd63a4dd3d056c834caf93199b7a",
          "message": "Update HelpMessage_3_SwitchesHeader description\n\nAfter adding support for both \"--\" and \"-\" switch indicators, the help\nmessage became outdated. It still mentiones only \"-\" and \"/\" indicators,\nwhich can be confusing.\nThis commit fixes it by updating the description of the main text.",
          "committedDate": "2021-03-01T18:14:31Z",
          "author": {
            "name": "Bartosz Klonowski",
            "email": "Bartosz-Klonowski@tlen.pl"
          }
        }
      },
      {
        "commit": {
          "oid": "1ef536c8b3e31f17ad5ebe8fd8d01763381cb0e4",
          "message": "Apply help message change to localizations",
          "committedDate": "2021-03-01T18:22:14Z",
          "author": {
            "name": "Bartosz Klonowski",
            "email": "Bartosz-Klonowski@tlen.pl"
          }
        }
      }
    ]
  },
  "comments": {
    "nodes": []
  },
  "reviewThreads": {
    "nodes": [
      {
        "comments": {
          "nodes": [
            {
              "body": "Tiny nit:\r\n```suggestion\r\n                     \"-switch\", \"/switch\", and \"--switch\".\r\n```\r\nI like Oxford commas \ud83d\ude09",
              "createdAt": "2021-03-02T16:21:03Z",
              "path": "src/MSBuild/Resources/Strings.resx",
              "diffHunk": "@@ -135,8 +135,8 @@ Copyright (C) Microsoft Corporation. All rights reserved.\n     </comment>\n   </data>\n   <data name=\"HelpMessage_3_SwitchesHeader\" UESanitized=\"true\" Visibility=\"Public\">\n-    <value>Switches:            Note that you can specify switches using both\n-                     \"-switch\" and \"/switch\".\n+    <value>Switches:            Note that you can specify switches using\n+                     \"-switch\", \"/switch\" and \"--switch\".",
              "author": {
                "login": "Forgind"
              }
            }
          ]
        }
      }
    ]
  }
}