{
  "number": 7143,
  "title": "Add GeneratePathProperty to xsd",
  "body": "",
  "state": "MERGED",
  "createdAt": "2021-12-11T03:33:42Z",
  "updatedAt": "2021-12-15T17:53:02Z",
  "closedAt": "2021-12-15T13:10:07Z",
  "mergedAt": "2021-12-15T13:10:07Z",
  "additions": 14,
  "deletions": 0,
  "changedFiles": 1,
  "headRefName": "dev/kirillo/generatePathProperty",
  "isDraft": false,
  "author": {
    "login": "KirillOsenkov"
  },
  "milestone": null,
  "assignees": {
    "nodes": []
  },
  "labels": [
    "merge-when-branch-open"
  ],
  "commits": {
    "nodes": [
      {
        "commit": {
          "oid": "56f04ae220c1489d738cc0dec2f9b98ffa3e1d8d",
          "message": "Add GeneratePathProperty to xsd",
          "committedDate": "2021-12-11T03:33:25Z",
          "author": {
            "name": "Kirill Osenkov",
            "email": "github@osenkov.com"
          }
        }
      },
      {
        "commit": {
          "oid": "7cb0353aba6c2dc4b6e6ef5dd45d1e8d2935c6b9",
          "message": "Update src/MSBuild/MSBuild/Microsoft.Build.CommonTypes.xsd",
          "committedDate": "2021-12-13T17:46:56Z",
          "author": {
            "name": "Forgind",
            "email": "Forgind@users.noreply.github.com"
          }
        }
      }
    ]
  },
  "comments": {
    "nodes": []
  },
  "reviewThreads": {
    "nodes": [
      {
        "comments": {
          "nodes": [
            {
              "body": "default?",
              "createdAt": "2021-12-13T04:00:25Z",
              "path": "src/MSBuild/MSBuild/Microsoft.Build.CommonTypes.xsd",
              "diffHunk": "@@ -207,6 +207,13 @@ elementFormDefault=\"qualified\">\n                   </xs:documentation>\n                 </xs:annotation>\n               </xs:element>\n+              <xs:element name=\"GeneratePathProperty\">\n+                <xs:annotation>\n+                  <xs:documentation>\n+                    <!-- _locID_text=\"PackageReference_GeneratePathProperty\" _locComment=\"\" -->Set to true to generate a Pkg* property that points to the restored location of the NuGet package contents",
              "author": {
                "login": "Forgind"
              }
            },
            {
              "body": "I was hoping someone more knowledgeable than me could push directly to this branch ;) \r\n\r\nDid you just fall into my trap? ",
              "createdAt": "2021-12-13T05:02:49Z",
              "path": "src/MSBuild/MSBuild/Microsoft.Build.CommonTypes.xsd",
              "diffHunk": "@@ -207,6 +207,13 @@ elementFormDefault=\"qualified\">\n                   </xs:documentation>\n                 </xs:annotation>\n               </xs:element>\n+              <xs:element name=\"GeneratePathProperty\">\n+                <xs:annotation>\n+                  <xs:documentation>\n+                    <!-- _locID_text=\"PackageReference_GeneratePathProperty\" _locComment=\"\" -->Set to true to generate a Pkg* property that points to the restored location of the NuGet package contents",
              "author": {
                "login": "KirillOsenkov"
              }
            },
            {
              "body": "```suggestion\r\n                    <!-- _locID_text=\"PackageReference_GeneratePathProperty\" _locComment=\"\" -->Set to true to generate a Pkg* property that points to the restored location of the NuGet package contents. If unset, does not create the property.\r\n```",
              "createdAt": "2021-12-13T17:46:35Z",
              "path": "src/MSBuild/MSBuild/Microsoft.Build.CommonTypes.xsd",
              "diffHunk": "@@ -207,6 +207,13 @@ elementFormDefault=\"qualified\">\n                   </xs:documentation>\n                 </xs:annotation>\n               </xs:element>\n+              <xs:element name=\"GeneratePathProperty\">\n+                <xs:annotation>\n+                  <xs:documentation>\n+                    <!-- _locID_text=\"PackageReference_GeneratePathProperty\" _locComment=\"\" -->Set to true to generate a Pkg* property that points to the restored location of the NuGet package contents",
              "author": {
                "login": "Forgind"
              }
            },
            {
              "body": "Maybe, but I do one-line changes from the browser to maximally ping you in the process \ud83d\ude42",
              "createdAt": "2021-12-13T17:47:27Z",
              "path": "src/MSBuild/MSBuild/Microsoft.Build.CommonTypes.xsd",
              "diffHunk": "@@ -207,6 +207,13 @@ elementFormDefault=\"qualified\">\n                   </xs:documentation>\n                 </xs:annotation>\n               </xs:element>\n+              <xs:element name=\"GeneratePathProperty\">\n+                <xs:annotation>\n+                  <xs:documentation>\n+                    <!-- _locID_text=\"PackageReference_GeneratePathProperty\" _locComment=\"\" -->Set to true to generate a Pkg* property that points to the restored location of the NuGet package contents",
              "author": {
                "login": "Forgind"
              }
            }
          ]
        }
      }
    ]
  }
}