{
  "number": 8553,
  "title": "Simplify pre cache",
  "body": "While reviewing one of rokonec's PRs, I noticed some things that looked like they could be made a little better. Some of these changes are innocuous and some might have serious perf impact one way or the other, so I don't think we should take this without measurements.",
  "state": "CLOSED",
  "createdAt": "2023-03-11T00:31:50Z",
  "updatedAt": "2023-06-02T19:03:38Z",
  "closedAt": "2023-06-02T19:03:38Z",
  "mergedAt": null,
  "additions": 29,
  "deletions": 40,
  "changedFiles": 1,
  "headRefName": "simplify-PRECache",
  "isDraft": true,
  "author": {
    "login": "Forgind"
  },
  "milestone": null,
  "assignees": {
    "nodes": []
  },
  "labels": [],
  "commits": {
    "nodes": [
      {
        "commit": {
          "oid": "cdcd53fc9ed51726a04eec99c11e3f79657cc33e",
          "message": "Simplify structures in PRECache",
          "committedDate": "2023-03-10T22:01:09Z",
          "author": {
            "name": "Forgind",
            "email": "Forgind@users.noreply.github.com"
          }
        }
      },
      {
        "commit": {
          "oid": "3100aff6c9b1fc839afa5f625909c9185932d0a8",
          "message": "Correct implicit reference discarding\n\nI'm not 100% sure about this...it's an actual change in behavior, but I think the original logic was wrong.",
          "committedDate": "2023-03-10T22:06:56Z",
          "author": {
            "name": "Forgind",
            "email": "Forgind@users.noreply.github.com"
          }
        }
      },
      {
        "commit": {
          "oid": "1fcc37246161cf0169da3355b38e88e8912b0d32",
          "message": "Revert one change",
          "committedDate": "2023-03-10T22:44:28Z",
          "author": {
            "name": "Forgind",
            "email": "Forgind@users.noreply.github.com"
          }
        }
      }
    ]
  },
  "comments": {
    "nodes": []
  },
  "reviewThreads": {
    "nodes": []
  }
}