{
  "number": 8705,
  "title": "Include placeholder for TF in loc strings",
  "body": "The double-bracing around this was missed in #8682.\n",
  "state": "MERGED",
  "createdAt": "2023-04-25T16:42:27Z",
  "updatedAt": "2023-04-25T18:00:40Z",
  "closedAt": "2023-04-25T18:00:38Z",
  "mergedAt": "2023-04-25T18:00:38Z",
  "additions": 27,
  "deletions": 27,
  "changedFiles": 14,
  "headRefName": "tf-in-locstring",
  "isDraft": false,
  "author": {
    "login": "rainersigwald"
  },
  "milestone": null,
  "assignees": {
    "nodes": []
  },
  "labels": [],
  "commits": {
    "nodes": [
      {
        "commit": {
          "oid": "5a3565ac98b0ed1c3fd5d32c6287577b29161996",
          "message": "Include placeholder for TF in loc strings\n\nThe double-bracing around this was missed in #8682.",
          "committedDate": "2023-04-25T16:42:04Z",
          "author": {
            "name": "Rainer Sigwald",
            "email": "raines@microsoft.com"
          }
        }
      }
    ]
  },
  "comments": {
    "nodes": []
  },
  "reviewThreads": {
    "nodes": []
  }
}