{
  "number": 8547,
  "title": "[Bugfix] Do not read Location of dynamic assemblies",
  "body": "Fixes https://dev.azure.com/devdiv/DevDiv/_workitems/edit/1761147\r\n\r\n### Context\r\n`Assembly.Location` throws in fullFW (https://learn.microsoft.com/en-us/dotnet/api/system.reflection.assembly.location?source=recommendations&view=net-7.0#exceptions)\r\nIt returns empty fron net5.0 up\r\n\r\n\r\n### Changes Made\r\nAltering the code to uniformly return empty path for dynamic assemblies (and prevent exceptions)\r\n",
  "state": "MERGED",
  "createdAt": "2023-03-08T11:48:24Z",
  "updatedAt": "2023-03-08T13:03:27Z",
  "closedAt": "2023-03-08T13:03:27Z",
  "mergedAt": "2023-03-08T13:03:27Z",
  "additions": 1,
  "deletions": 1,
  "changedFiles": 1,
  "headRefName": "exp/log-dynamic-assemblies",
  "isDraft": false,
  "author": {
    "login": "JanKrivanek"
  },
  "milestone": null,
  "assignees": {
    "nodes": []
  },
  "labels": [],
  "commits": {
    "nodes": [
      {
        "commit": {
          "oid": "7742e8e464768a0528159c74c73d29318fe81ea5",
          "message": "Do not read Location of dynamic assemblies",
          "committedDate": "2023-03-08T11:44:54Z",
          "author": {
            "name": "Jan Krivanek",
            "email": "jankrivanek@microsoft.com"
          }
        }
      }
    ]
  },
  "comments": {
    "nodes": []
  },
  "reviewThreads": {
    "nodes": []
  }
}