{
  "number": 8079,
  "title": "Updated MSBuild version in global.json",
  "body": "Fixes signing validation in our pipeline.",
  "state": "MERGED",
  "createdAt": "2022-10-20T15:05:09Z",
  "updatedAt": "2022-10-20T16:05:39Z",
  "closedAt": "2022-10-20T16:05:38Z",
  "mergedAt": "2022-10-20T16:05:38Z",
  "additions": 2,
  "deletions": 2,
  "changedFiles": 1,
  "headRefName": "exp/mipavlik/sdk-rc2",
  "isDraft": false,
  "author": {
    "login": "MichalPavlik"
  },
  "milestone": null,
  "assignees": {
    "nodes": []
  },
  "labels": [],
  "commits": {
    "nodes": [
      {
        "commit": {
          "oid": "8fe9ced654ee558e7adbcb6100a88d2d23c2adcf",
          "message": "Updated MSBuild version in global.json",
          "committedDate": "2022-10-20T14:36:46Z",
          "author": {
            "name": "Michal Pavlik",
            "email": "mipavlik@microsoft.com"
          }
        }
      },
      {
        "commit": {
          "oid": "bebf6b70458e66fe81eeaacda889277881d425ca",
          "message": "Updated vs->version",
          "committedDate": "2022-10-20T15:11:01Z",
          "author": {
            "name": "Michal Pavlik",
            "email": "mipavlik@microsoft.com"
          }
        }
      }
    ]
  },
  "comments": {
    "nodes": []
  },
  "reviewThreads": {
    "nodes": [
      {
        "comments": {
          "nodes": [
            {
              "body": "Let's change this one too please.",
              "createdAt": "2022-10-20T15:09:00Z",
              "path": "global.json",
              "diffHunk": "@@ -7,7 +7,7 @@\n     \"vs\": {\n       \"version\": \"17.2.1\"",
              "author": {
                "login": "rainersigwald"
              }
            }
          ]
        }
      }
    ]
  }
}