{
  "number": 9423,
  "title": "Fix missed errors appearance on restore",
  "body": "",
  "state": "CLOSED",
  "createdAt": "2023-11-15T15:37:36Z",
  "updatedAt": "2023-11-16T07:36:54Z",
  "closedAt": "2023-11-15T15:55:44Z",
  "mergedAt": null,
  "additions": 17,
  "deletions": 7,
  "changedFiles": 1,
  "headRefName": "dev/ykovalova/fix_errors_apperance_on_restore",
  "isDraft": true,
  "author": {
    "login": "YuliiaKovalova"
  },
  "milestone": null,
  "assignees": {
    "nodes": []
  },
  "labels": [],
  "commits": {
    "nodes": [
      {
        "commit": {
          "oid": "67b804e54e5312fafdd4ffd82c1d2922eeefd7a7",
          "message": "fix nuget message appearance",
          "committedDate": "2023-11-08T16:16:16Z",
          "author": {
            "name": "YuliiaKovalova",
            "email": "ykovalova@microsoft.com"
          }
        }
      },
      {
        "commit": {
          "oid": "179e48737d52484f33daee29f06c37985b9427c9",
          "message": "fix review comments",
          "committedDate": "2023-11-09T16:57:33Z",
          "author": {
            "name": "YuliiaKovalova",
            "email": "ykovalova@microsoft.com"
          }
        }
      },
      {
        "commit": {
          "oid": "6065898710eca199561f1de3c09a5db4be2e854f",
          "message": "add unit tests",
          "committedDate": "2023-11-09T18:01:31Z",
          "author": {
            "name": "YuliiaKovalova",
            "email": "ykovalova@microsoft.com"
          }
        }
      },
      {
        "commit": {
          "oid": "a150e71b213d21e611f71912553291d60899387c",
          "message": "fix comments",
          "committedDate": "2023-11-09T18:36:39Z",
          "author": {
            "name": "YuliiaKovalova",
            "email": "ykovalova@microsoft.com"
          }
        }
      },
      {
        "commit": {
          "oid": "14d7d68fd7aef371cc6edabd96e200205bbf1ea0",
          "message": "use full source-generator",
          "committedDate": "2023-11-10T12:49:40Z",
          "author": {
            "name": "YuliiaKovalova",
            "email": "ykovalova@microsoft.com"
          }
        }
      },
      {
        "commit": {
          "oid": "3fc6e65fcb3ff8ad5f31f999ce4cc9cbf855077e",
          "message": "fix review comments",
          "committedDate": "2023-11-13T16:15:54Z",
          "author": {
            "name": "YuliiaKovalova",
            "email": "ykovalova@microsoft.com"
          }
        }
      },
      {
        "commit": {
          "oid": "dc343ef1141494bc731389ae31be0f17c2310aa6",
          "message": "fix tests",
          "committedDate": "2023-11-13T16:40:35Z",
          "author": {
            "name": "YuliiaKovalova",
            "email": "ykovalova@microsoft.com"
          }
        }
      },
      {
        "commit": {
          "oid": "4804d3bbf901b9899366f33b50beedf5ee23fa10",
          "message": "fix review comment",
          "committedDate": "2023-11-14T13:04:43Z",
          "author": {
            "name": "YuliiaKovalova",
            "email": "ykovalova@microsoft.com"
          }
        }
      },
      {
        "commit": {
          "oid": "52e49cc6cb02d21d22807b3cf36ce861616b4abc",
          "message": "address more comments",
          "committedDate": "2023-11-14T13:16:51Z",
          "author": {
            "name": "YuliiaKovalova",
            "email": "ykovalova@microsoft.com"
          }
        }
      },
      {
        "commit": {
          "oid": "3d5d99d1a002eba70b2bde7149be7e416b0bd4bd",
          "message": "Merge branch 'dotnet:main' into dev/ykovalova/fix_errors_apperance_on_restore",
          "committedDate": "2023-11-15T13:15:48Z",
          "author": {
            "name": "YuliiaKovalova",
            "email": "95473390+YuliiaKovalova@users.noreply.github.com"
          }
        }
      },
      {
        "commit": {
          "oid": "0892730d31f28b1a39baff3f2a7ebeeeeea786cb",
          "message": "add dispaying error messages not assosiated with tracked projects",
          "committedDate": "2023-11-15T13:51:25Z",
          "author": {
            "name": "YuliiaKovalova",
            "email": "ykovalova@microsoft.com"
          }
        }
      },
      {
        "commit": {
          "oid": "a1aa7117597484aec32ff36844b92e71d9137ba3",
          "message": "include project file name in output",
          "committedDate": "2023-11-15T15:36:49Z",
          "author": {
            "name": "YuliiaKovalova",
            "email": "ykovalova@microsoft.com"
          }
        }
      }
    ]
  },
  "comments": {
    "nodes": []
  },
  "reviewThreads": {
    "nodes": []
  }
}