{
  "number": 9370,
  "title": "add custom task",
  "body": "Fixes #\r\n\r\n### Context\r\n\r\n\r\n### Changes Made\r\n\r\n\r\n### Testing\r\n\r\n\r\n### Notes\r\n",
  "state": "CLOSED",
  "createdAt": "2023-10-30T10:35:57Z",
  "updatedAt": "2024-03-18T15:12:56Z",
  "closedAt": "2023-11-13T20:05:20Z",
  "mergedAt": null,
  "additions": 377,
  "deletions": 57,
  "changedFiles": 8,
  "headRefName": "exp/ykovalova/add_new_target",
  "isDraft": true,
  "author": {
    "login": "YuliiaKovalova"
  },
  "milestone": null,
  "assignees": {
    "nodes": []
  },
  "labels": [],
  "commits": {
    "nodes": [
      {
        "commit": {
          "oid": "df3b6b61ac5cd5f28147188d139c8831c34c75e1",
          "message": "add custom task",
          "committedDate": "2023-10-30T10:35:36Z",
          "author": {
            "name": "YuliiaKovalova",
            "email": "ykovalova@microsoft.com"
          }
        }
      },
      {
        "commit": {
          "oid": "911e6aaa842c9e5697bcbcbdaeb5c76ba89fda8f",
          "message": "Merge remote-tracking branch 'origin/main' into exp/ykovalova/add_new_target",
          "committedDate": "2023-10-31T17:15:03Z",
          "author": {
            "name": "YuliiaKovalova",
            "email": "ykovalova@microsoft.com"
          }
        }
      },
      {
        "commit": {
          "oid": "820b32d1229c1e266a8c6387ccb4cbdda448276c",
          "message": "add files to csproj",
          "committedDate": "2023-10-31T19:36:41Z",
          "author": {
            "name": "YuliiaKovalova",
            "email": "ykovalova@microsoft.com"
          }
        }
      },
      {
        "commit": {
          "oid": "0df1ce941c21a27e9d66d341d8c9c1a607472a9b",
          "message": "add missed changes",
          "committedDate": "2023-10-31T19:45:23Z",
          "author": {
            "name": "YuliiaKovalova",
            "email": "ykovalova@microsoft.com"
          }
        }
      },
      {
        "commit": {
          "oid": "f2f565c6f72d565eebbdbef667aff9530e4e2f00",
          "message": "add path existence check",
          "committedDate": "2023-11-01T14:50:54Z",
          "author": {
            "name": "YuliiaKovalova",
            "email": "ykovalova@microsoft.com"
          }
        }
      },
      {
        "commit": {
          "oid": "5357a9f3d09f55dcffca007354fa3c30da992a14",
          "message": "update check",
          "committedDate": "2023-11-01T15:05:43Z",
          "author": {
            "name": "YuliiaKovalova",
            "email": "ykovalova@microsoft.com"
          }
        }
      },
      {
        "commit": {
          "oid": "c39dd450fa069d262d348116d07a51a155fab75d",
          "message": "remove extra condition",
          "committedDate": "2023-11-01T17:05:38Z",
          "author": {
            "name": "YuliiaKovalova",
            "email": "ykovalova@microsoft.com"
          }
        }
      }
    ]
  },
  "comments": {
    "nodes": []
  },
  "reviewThreads": {
    "nodes": []
  }
}